pyneoncli/__init__.py
pyneoncli/clicommands.py
pyneoncli/clidispatcher.py
pyneoncli/clilist.py
pyneoncli/climain.py
pyneoncli/colortext.py
pyneoncli/configfile.py
pyneoncli/endpoint_template.json
pyneoncli/exceptions.py
pyneoncli/msg.py
pyneoncli/neon.py
pyneoncli/neonapi.py
pyneoncli/neonapiexceptions.py
pyneoncli/neonliterals.py
pyneoncli/printer.py
pyneoncli/rawneonapi.py
pyneoncli/requester.py
pyneoncli/threadedcreate.py
pyneoncli/threadedneonapi.py
pyneoncli/version.py
pyneoncli-0.1.1.dist-info/LICENSE
pyneoncli-0.1.1.dist-info/METADATA
pyneoncli-0.1.1.dist-info/WHEEL
pyneoncli-0.1.1.dist-info/entry_points.txt
pyneoncli-0.1.1.dist-info/RECORD
