Metadata-Version: 2.1
Name: pyneoncli
Version: 0.1.1
Summary: A Python CLI for the Neon API
License: Apache-2.0
Author: Joe Drumgoole
Author-email: Joe.Drumgoole@neon.tech
Requires-Python: >=3.8,<4.0
Classifier: License :: OSI Approved :: Apache Software License
Classifier: Programming Language :: Python :: 3
Classifier: Programming Language :: Python :: 3.8
Classifier: Programming Language :: Python :: 3.9
Classifier: Programming Language :: Python :: 3.10
Classifier: Programming Language :: Python :: 3.11
Requires-Dist: colorama (>=0.4.6,<0.5.0)
Requires-Dist: configargparse (>=1.5.3,<2.0.0)
Requires-Dist: poetry (>=1.5.1,<2.0.0)
Requires-Dist: pygments (>=2.15.1,<3.0.0)
Requires-Dist: python-dotenv (>=1.0.0,<2.0.0)
Requires-Dist: requests (>=2.31.0,<3.0.0)
